odoo10_addon_mrp_progress_button-10.0.1.0.0-py2.7-nspkg.pth
odoo/addons/mrp_progress_button/README.rst
odoo/addons/mrp_progress_button/__init__.py
odoo/addons/mrp_progress_button/__manifest__.py
odoo/addons/mrp_progress_button/models/__init__.py
odoo/addons/mrp_progress_button/models/mrp_production.py
odoo/addons/mrp_progress_button/tests/__init__.py
odoo/addons/mrp_progress_button/tests/test_progress_button.py
odoo/addons/mrp_progress_button/views/production.xml
odoo10_addon_mrp_progress_button-10.0.1.0.0.dist-info/DESCRIPTION.rst
odoo10_addon_mrp_progress_button-10.0.1.0.0.dist-info/METADATA
odoo10_addon_mrp_progress_button-10.0.1.0.0.dist-info/RECORD
odoo10_addon_mrp_progress_button-10.0.1.0.0.dist-info/WHEEL
odoo10_addon_mrp_progress_button-10.0.1.0.0.dist-info/metadata.json
odoo10_addon_mrp_progress_button-10.0.1.0.0.dist-info/namespace_packages.txt
odoo10_addon_mrp_progress_button-10.0.1.0.0.dist-info/top_level.txt
