Metadata-Version: 2.0
Name: odoo10-addon-mrp-progress-button
Version: 10.0.1.0.0
Summary: Add a button on MO to make the MO state 'In Progress'
Home-page: https://akretion.com/
Author: Akretion, Odoo Community Association (OCA)
Author-email: support@odoo-community.org
License: AGPL-3
Platform: UNKNOWN
Classifier: Programming Language :: Python
Classifier: Framework :: Odoo
Classifier: License :: OSI Approved :: GNU Affero General Public License v3
Requires-Python: ~=2.7
Requires-Dist: odoo (<10.1dev,>=10.0)
